{
  "6285147348859": {
    "name": "tianboys",
    "password": "v6"
  },
  "6282183329589": {
    "name": "Giva",
    "password": "16"
  },
  "6285378724705": {
    "name": "Giva",
    "password": "16"
  },
  "62895634790205": {
    "name": "de",
    "password": "de"
  },
  "6285279925685": {
    "name": "han",
    "password": "titid"
  },
  "6283869801717": {
    "name": "de",
    "password": "de"
  },
  "6289530950375": {
    "name": "dafa",
    "password": "30"
  },
  "37258883215": {
    "name": "dann",
    "password": "1"
  },
  "628388952934": {
    "name": "vinz",
    "password": "10"
  },
  "6281345566020": {
    "name": "Vammz",
    "password": "200"
  },
  "6287838436270": {
    "name": "Alya",
    "password": "anjay"
  },
  "6285798733841": {
    "name": "alwaysriky",
    "password": "alwaysriky01"
  },
  "6287823358993": {
    "name": "rexxa",
    "password": "rexxa"
  },
  "60128200414": {
    "name": "rizz",
    "password": "rizz"
  },
  "62895806115030": {
    "name": "xenbot",
    "password": "20"
  },
  "6282121449919": {
    "name": "fari",
    "password": "13"
  },
  "6281263405745": {
    "name": "xenn",
    "password": "2"
  },
  "6283874021937": {
    "name": "zora",
    "password": "zora"
  },
  "6281384572700": {
    "name": "rapsboys",
    "password": "rapsboys"
  },
  "6283147461644": {
    "name": "vinz",
    "password": "10"
  },
  "6283147462086": {
    "name": "vinz",
    "password": "10"
  },
  "6281220321959": {
    "name": "nokos",
    "password": "unli"
  },
  "6285262105013": {
    "name": "tianmalau",
    "password": "16"
  },
  "628568619496": {
    "name": "rapzie",
    "password": "rapzie"
  },
  "628988106426": {
    "name": "aan",
    "password": "1"
  },
  "6283197242161": {
    "name": "han",
    "password": "12"
  },
  "6283878996150": {
    "name": "rapboys",
    "password": "rapboys12"
  },
  "62895404719141": {
    "name": "aan",
    "password": "1"
  }
}